jupyterclearcheck-0.2.1.dist-info/METADATA
jupyterclearcheck-0.2.1.dist-info/WHEEL
jupyterclearcheck-0.2.1.dist-info/entry_points.txt
jupyterclearcheck-0.2.1.dist-info/licenses/LICENSE
jupyterclearcheck/__init__.py
jupyterclearcheck/__main__.py
jupyterclearcheck/cli.py
jupyterclearcheck/utils/__init__.py
jupyterclearcheck/utils/notebook_exception.py
jupyterclearcheck/utils/notebook_path.py
jupyterclearcheck-0.2.1.dist-info/RECORD
