Metadata-Version: 2.1
Name: JupyterClearCheck
Version: 0.2.1
Summary: A Python CLI to check that a Jupyter Notebook's Outputs' have been cleared.
Home-page: https://github.com/guru-desh/JupyterClearCheck
Author-Email: Gururaj Deshpande <gurudesh@gatech.edu>
License: MIT
Project-URL: Homepage, https://github.com/guru-desh/JupyterClearCheck
Requires-Python: >=3.9
Requires-Dist: nbformat>=5.10.4
